pysuggestify/PMF.py
pysuggestify/__init__.py
pysuggestify/version.py
pysuggestify-0.1.dist-info/LICENSE
pysuggestify-0.1.dist-info/METADATA
pysuggestify-0.1.dist-info/WHEEL
pysuggestify-0.1.dist-info/top_level.txt
pysuggestify-0.1.dist-info/RECORD
