Metadata-Version: 2.1
Name: pysuggestify
Version: 0.1
Summary: A user-friendly Python package for building recommendation systems based on PMF algorithm.
Home-page: https://github.com/msoczi/pysuggestify
Author: Mateusz Soczewka
Author-email: msoczewkas@gmail.com
Project-URL: Bug Tracker, https://github.com/msoczi/pysuggestify/issues
Classifier: License :: OSI Approved :: MIT License
Classifier: Programming Language :: Python :: 3
Classifier: Programming Language :: Python :: 3.8
Classifier: Programming Language :: Python :: 3.9
Classifier: Operating System :: OS Independent
Requires-Python: >=3.8
License-File: LICENSE
Requires-Dist: pandas (>=1.5.0)
Requires-Dist: numpy (>=1.21.4)
Requires-Dist: matplotlib (>=3.4.3)
